pycleverbot
