Metadata-Version: 1.0
Name: pycleverbot
Version: 0.2
Summary: cleverbot api
Home-page: UNKNOWN
Author: jarbasAI
Author-email: jarbasai@mailfence.com
License: Apache
Platform: UNKNOWN
